aaaSvg/__init__.py
aaaSvg/svg.py
aaaSvg-0.1.8.dist-info/LICENSE
aaaSvg-0.1.8.dist-info/METADATA
aaaSvg-0.1.8.dist-info/WHEEL
aaaSvg-0.1.8.dist-info/top_level.txt
aaaSvg-0.1.8.dist-info/RECORD
